MoveMyMusic/VK.py
MoveMyMusic/__init__.py
MoveMyMusic/__main__.py
MoveMyMusic/config.py
MoveMyMusic/spotify.py
MoveMyMusic/yandexmusic.py
Move_My_Music-0.0.2.dev11.dist-info/LICENSE
Move_My_Music-0.0.2.dev11.dist-info/METADATA
Move_My_Music-0.0.2.dev11.dist-info/WHEEL
Move_My_Music-0.0.2.dev11.dist-info/entry_points.txt
Move_My_Music-0.0.2.dev11.dist-info/top_level.txt
Move_My_Music-0.0.2.dev11.dist-info/RECORD
