Metadata-Version: 2.1
Name: Move-My-Music
Version: 0.0.2.dev11
Summary: Script to migrate music between platforms
Home-page: https://github.com/Addic7edBoy/MoveMyMusic
Author: Max Medvedev
Author-email: medve.mk@gmail.com
License: UNKNOWN
Platform: UNKNOWN
Classifier: Programming Language :: Python :: 3
Classifier: License :: OSI Approved :: MIT License
Classifier: Operating System :: OS Independent
Requires-Python: >=3.6
Requires-Dist: vk-api (==11.8.0)
Requires-Dist: yandex-music (==1.0.0)
Requires-Dist: spotipy (==2.16.0)
Requires-Dist: six
Requires-Dist: beautifulsoup4
Requires-Dist: requests
Requires-Dist: python-dotenv
